gdllm/__init__.py
gdllm/abstract/__init__.py
gdllm/abstract/config.py
gdllm/abstract/llm.py
gdllm/abstract/message.py
gdllm/abstract/tool.py
gdllm/implementations/__init__.py
gdllm/implementations/anthropic/__init__.py
gdllm/implementations/anthropic/config.py
gdllm/implementations/anthropic/llm.py
gdllm/implementations/anthropic/message.py
gdllm/implementations/anthropic/tool.py
gdllm/implementations/deepseek/__init__.py
gdllm/implementations/deepseek/config.py
gdllm/implementations/deepseek/llm.py
gdllm/implementations/deepseek/message.py
gdllm/implementations/deepseek/tool.py
gdllm/implementations/google/__init__.py
gdllm/implementations/google/config.py
gdllm/implementations/google/llm.py
gdllm/implementations/google/message.py
gdllm/implementations/google/tool.py
gdllm/implementations/openai/__init__.py
gdllm/implementations/openai/config.py
gdllm/implementations/openai/llm.py
gdllm/implementations/openai/message.py
gdllm/implementations/openai/tool.py
gdllm/util/__init__.py
gdllm/util/conversation.py
gdllm/util/tool_registry.py
gdllm-0.2.1.dist-info/METADATA
gdllm-0.2.1.dist-info/WHEEL
gdllm-0.2.1.dist-info/entry_points.txt
gdllm-0.2.1.dist-info/licenses/LICENSE
gdllm-0.2.1.dist-info/RECORD
